{
  "generator-jhipster": {
    "promptValues": {
      "packageName": "com.yahoo.quotes",
      "nativeLanguage": "en"
    },
    "jhipsterVersion": "6.10.1",
    "applicationType": "monolith",
    "baseName": "yahoo",
    "packageName": "com.yahoo.quotes",
    "packageFolder": "com/yahoo/quotes",
    "serverPort": "8080",
    "authenticationType": "session",
    "cacheProvider": "ehcache",
    "enableHibernateCache": true,
    "websocket": false,
    "databaseType": "sql",
    "devDatabaseType": "h2Disk",
    "prodDatabaseType": "postgresql",
    "searchEngine": false,
    "messageBroker": false,
    "serviceDiscoveryType": false,
    "buildTool": "maven",
    "enableSwaggerCodegen": false,
    "rememberMeKey": "16c03cddcee8b470a0ad70cdbb31ba6d704eb133a228dd1d6bc7219a96666f76a8f990cfce36cb0135da9251e28bb40a47ba",
    "embeddableLaunchScript": false,
    "useSass": true,
    "clientPackageManager": "npm",
    "clientFramework": "angularX",
    "clientTheme": "none",
    "clientThemeVariant": "",
    "creationTimestamp": 1616097327124,
    "testFrameworks": ["cucumber", "protractor"],
    "jhiPrefix": "jhi",
    "entitySuffix": "",
    "dtoSuffix": "DTO",
    "otherModules": [],
    "enableTranslation": true,
    "nativeLanguage": "en",
    "languages": ["en", "es"],
    "blueprints": []
  }
}
